pypolkadot-0.2.5.dist-info/METADATA
pypolkadot-0.2.5.dist-info/WHEEL
pypolkadot-0.2.5.dist-info/licenses/LICENSE
pypolkadot/.DS_Store
pypolkadot/__init__.py
pypolkadot/__pycache__/__init__.cpython-312.pyc
pypolkadot/_pypolkadot.cpython-312-darwin.so
pypolkadot/chain_specs/.DS_Store
pypolkadot/chain_specs/asset-hub-kusama.json
pypolkadot/chain_specs/asset-hub-polkadot.json
pypolkadot/chain_specs/kusama.json
pypolkadot/chain_specs/paseo-asset-hub.smol.json
pypolkadot/chain_specs/paseo.raw.smol.json
pypolkadot/chain_specs/polkadot.json
pypolkadot/py.typed
pypolkadot-0.2.5.dist-info/RECORD
