Metadata-Version: 2.4
Name: pypolkadot
Version: 0.2.5
Classifier: Development Status :: 3 - Alpha
Classifier: Intended Audience :: Developers
Classifier: License :: OSI Approved :: Apache Software License
Classifier: Programming Language :: Python :: 3
Classifier: Programming Language :: Python :: 3.9
Classifier: Programming Language :: Python :: 3.10
Classifier: Programming Language :: Python :: 3.11
Classifier: Programming Language :: Python :: 3.12
Classifier: Programming Language :: Rust
Classifier: Topic :: Software Development :: Libraries
Requires-Dist: pytest ; extra == 'dev'
Provides-Extra: dev
License-File: LICENSE
Summary: Python light client for Polkadot/Substrate via smoldot
Keywords: polkadot,substrate,blockchain,light-client,smoldot,web3
License: GPL-3.0
Requires-Python: >=3.9
Project-URL: Homepage, https://code.jedda.eu/pypolkadot/
Project-URL: Documentation, https://code.jedda.eu/pypolkadot/
Project-URL: Repository, https://code.jedda.eu/pypolkadot/
